{
  "posts": [
    {
      "id": 0,
      "title": "Smart Guns: Gun Control That's Good for the Gun Business",
      "vote": 0
    },
    {
      "title": "Wells Fargo Called Out by Teachers Union Over Gun Industry Ties",
      "vote": "0",
      "id": 1
    },
    {
      "title": "Students Stage Walkouts Protesting Gun Violence on Columbine Anniversary",
      "vote": "0",
      "id": 2
    },
    {
      "title": "Why Are Gun Sales Falling?",
      "vote": "0",
      "id": 3
    },
    {
      "title": "Even in Chicago, Plan to Push Gun Control on Wall Street Stalls",
      "vote": "0",
      "id": 4
    },
    {
      "title": "Michigan Dumps Its Gun Shares",
      "vote": "0",
      "id": 5
    },
    {
      "title": "Trump Embrace of NRA Brings Old Obstacle to Latest Gun Debate",
      "vote": "0",
      "id": 6
    },
    {
      "title": "Trump Meets With NRA at White House a Day After Urging Gun Curbs",
      "vote": "0",
      "id": 7
    },
    {
      "title": "Florida Shooting: Second Amendment Does Not Block Gun Control",
      "vote": "0",
      "id": 8
    },
    {
      "title": "Gun Sales Are Down, So Why Did Gun Stocks Just Go Up?",
      "vote": "0",
      "id": 9
    },
    {
      "title": "Federal Judge Upholds Massachusetts’s Assault-Weapons Ban",
      "vote": "0",
      "id": 10
    },
    {
      "title": "Supreme Court Lets California’s Gun-Buying Waiting Period Stand",
      "vote": "0",
      "id": 11
    },
    {
      "title": "After Florida School Shooting, Americans Must Fight for Gun Laws",
      "vote": "0",
      "id": 12
    },
    {
      "title": "Kroger's Fred Meyer Stores Announce Plan to Abandon Gun Business",
      "vote": "0",
      "id": 13
    },
    {
      "title": "In World's Murder Capital, Brazilians Are Ready to Buy Guns",
      "vote": "0",
      "id": 14
    },
    {
      "title": "Portraits from the March for Our Lives in Washington",
      "vote": "0",
      "id": 15
    },
    {
      "title": "Parkland students: We are trying to succeed where the adults have failed",
      "vote": "0",
      "id": 16
    },
    {
      "title": "Gun owners are talking about gun control. Stop and listen",
      "vote": "0",
      "id": 17
    },
    {
      "title": "Even Republican gun owners don't agree on gun policy",
      "vote": "0",
      "id": 18
    },
    {
      "title": "YouTube restricts gun videos",
      "vote": "0",
      "id": 19
    },
    {
      "title": "There's a gun for every American. But less than a third own guns.",
      "vote": "0",
      "id": 20
    },
    {
      "title": "How France cut its per capita gun ownership in half",
      "vote": "0",
      "id": 21
    },
    {
      "title": "Gun laws that actually prevent child injuries, new study shows",
      "vote": "0",
      "id": 22
    },
    {
      "title": "How Remington became a icon among American gunmakers",
      "vote": "0",
      "id": 23
    },
    {
      "title": "Gun-rights supporters hand out rifle magazines at a rally in Vermont",
      "vote": "0",
      "id": 24
    },
    {
      "title": "Vermont governor signs sweeping gun control measures",
      "vote": "0",
      "id": 25
    },
    {
      "title": "What to expect from Friday's massive National School Walkout",
      "vote": "0",
      "id": 26
    },
    {
      "title": "BofA's Gun Dilemma Is Just the Start",
      "vote": "0",
      "id": 27
    },
    {
      "title": "If Sports Betting's Going to Be Legal, Major Leagues Want a Cut",
      "vote": "0",
      "id": 28
    },
    {
      "title": "China to Encourage Horse Racing, Expand Sports Lottery in Hainan",
      "vote": "0",
      "id": 29
    },
    {
      "title": "Tennis Match-Fixing Probe Targets Growing Market for Sports Data",
      "vote": "0",
      "id": 30
    },
    {
      "title": "Sponsors Are Sick of Australian Sports Stars Behaving Badly",
      "vote": "0",
      "id": 31
    },
    {
      "title": "Will Supreme Court Bless Sports Wagers? Casinos Are Placing Bets",
      "vote": "0",
      "id": 32
    },
    {
      "title": "A $300,000 Watch for Your $3.26 Million Sports Car",
      "vote": "0",
      "id": 33
    },
    {
      "title": "How Big Sports Leagues Push Junk Food on Kids",
      "vote": "0",
      "id": 34
    },
    {
      "title": "Defectors Reveal Harsh Life for North Korea's Sports Ambassadors",
      "vote": "0",
      "id": 35
    },
    {
      "title": "European Sports Ditch Female Hostesses in #MeToo Ripple Effect",
      "vote": "0",
      "id": 36
    },
    {
      "title": "Las Vegas Sets Bond Sale for the New Raiders' Stadium: Joe Mysak",
      "vote": "0",
      "id": 37
    },
    {
      "title": "Twitter Inks More Than 30 Video Deals With Disney, NBC, Viacom",
      "vote": "0",
      "id": 38
    },
    {
      "title": "Vegas, Baby! NHL's Golden Knights Score in First Year (Podcast)",
      "vote": "0",
      "id": 39
    },
    {
      "title": "A Car Obsessive Who Spent $1 Million to Update an Infamous Ferrari",
      "vote": "0",
      "id": 40
    },
    {
      "title": "URGENT: The Latest: Judge Won't Punish Dad Who Charged At Nassar",
      "vote": "0",
      "id": 41
    },
    {
      "title": "ESPN President Stepped Down After Extortion Plot",
      "vote": "0",
      "id": 42
    },
    {
      "title": "Nike Says It 'Acted Swiftly' After It Heard of Behavioral Issues",
      "vote": "0",
      "id": 43
    },
    {
      "title": "U.S. Senator: Give Me ‘Five Minutes’ With Larry Nassar",
      "vote": "0",
      "id": 44
    },
    {
      "title": "England's Premier League Teams Have Never Been So Profitable",
      "vote": "0",
      "id": 45
    },
    {
      "title": "What a shot! 28 amazing sports photos",
      "vote": "0",
      "id": 46
    },
    {
      "title": "What a shot! 24 amazing sports photos",
      "vote": "0",
      "id": 47
    },
    {
      "title": "What a shot! 25 amazing sports photos",
      "vote": "0",
      "id": 48
    },
    {
      "title": "What a shot! 21 amazing sports photos",
      "vote": "0",
      "id": 49
    },
    {
      "title": "What a shot! 23 amazing sports photos",
      "vote": "0",
      "id": 50
    },
    {
      "title": "76% of sports sponsorships tied to junk food, study says",
      "vote": "0",
      "id": 51
    },
    {
      "title": "US Olympian: Why young women need sports — and funding",
      "vote": "0",
      "id": 52
    },
    {
      "title": "Brazilian sports journalists may be having their #MeToo moment",
      "vote": "0",
      "id": 53
    },
    {
      "title": "What's at stake in the Supreme Court's sports betting decision",
      "vote": "0",
      "id": 54
    },
    {
      "title": "From soccer to sake, why Hidetoshi Nakata is on a cultural mission",
      "vote": "0",
      "id": 55
    },
    {
      "title": "Fox wants to cut commercial time to 2 minutes per hour",
      "vote": "0",
      "id": 56
    },
    {
      "title": "How DraftKings is prepping for the Supreme Court's sports betting decision",
      "vote": "0",
      "id": 57
    },
    {
      "title": "NBC Sports to air Indianapolis 500 for first time in 2019",
      "vote": "0",
      "id": 58
    },
    {
      "title": "What Happens When Business and Politics Mix - Bloomberg",
      "vote": "0",
      "id": 59
    },
    {
      "title": "Bloomberg's New Global Politics Weekend Reads",
      "vote": "0",
      "id": 60
    },
    {
      "title": "Politics Is Now a Risk in Sweden, $10 Billion Fund Manager Warns",
      "vote": "0",
      "id": 61
    },
    {
      "title": "Murdoch Gears Up to Fight for Sky",
      "vote": "0",
      "id": 62
    },
    {
      "title": "Spain Is Booming and Now Voters Turn Against the Prime Minister",
      "vote": "0",
      "id": 63
    },
    {
      "title": "Politics Can Be Murderous in South Africa's Port City of Durban",
      "vote": "0",
      "id": 64
    },
    {
      "title": "What Is ‘The Memo,’ and Why Is Washington Abuzz?",
      "vote": "0",
      "id": 65
    },
    {
      "title": "Ex-HSBC Worker Extradition Risks Crashing Into Spanish Politics",
      "vote": "0",
      "id": 66
    },
    {
      "title": "Surviving the Game of Thrones That Is Malaysian Politics",
      "vote": "0",
      "id": 67
    },
    {
      "title": "Illinois Faces Rising Yields as Politics Cloud Return to Market",
      "vote": "0",
      "id": 68
    },
    {
      "title": "Trump Slams Comey for Exonerating Clinton Based on Politics",
      "vote": "0",
      "id": 69
    },
    {
      "title": "ECB Looks Down Stimulus Exit Path as Politics Threaten Economy",
      "vote": "0",
      "id": 70
    },
    {
      "title": "Amazon's HQ2 Search Is About Politics, Too - Bloomberg",
      "vote": "0",
      "id": 71
    },
    {
      "title": "U.K.'s May Walks Tightrope Between Trade, Politics in China",
      "vote": "0",
      "id": 72
    },
    {
      "title": "The Politics of 'Roseanne' Are Recognition and Empathy - Bloomberg",
      "vote": "0",
      "id": 73
    },
    {
      "title": "How Even a Convicted Lula Might Sway Brazilian Politics",
      "vote": "0",
      "id": 74
    },
    {
      "title": "Pakistan to Contest Alleged Terror Group Entering Politics",
      "vote": "0",
      "id": 75
    },
    {
      "title": "Why Nigeria’s Central Bank Is Paralyzed by Politics: QuickTake",
      "vote": "0",
      "id": 76
    },
    {
      "title": "The week in politics",
      "vote": "0",
      "id": 77
    }
  ]
}